luis_v_subtitler/__init__.py
luis_v_subtitler/__main__.py
luis_v_subtitler/cli.py
luis_v_subtitler/language_identification.py
luis_v_subtitler/save_subtitles.py
luis_v_subtitler/subtitler.py
luis_v_subtitler/utils.py
luis_v_subtitler/whisperx_transcribe.py
luis_v_subtitler-0.1.10.dist-info/AUTHORS.rst
luis_v_subtitler-0.1.10.dist-info/LICENSE
luis_v_subtitler-0.1.10.dist-info/METADATA
luis_v_subtitler-0.1.10.dist-info/WHEEL
luis_v_subtitler-0.1.10.dist-info/dependency_links.txt
luis_v_subtitler-0.1.10.dist-info/entry_points.txt
luis_v_subtitler-0.1.10.dist-info/top_level.txt
luis_v_subtitler-0.1.10.dist-info/RECORD
